{
  "source": "FCInterNews (Italian)",
  "generated_utc": "2025-08-21T16:26:54.132725+00:00",
  "count": 60,
  "articles": [
    {
      "id": "e038c7181420ca54eaa73beff550e264",
      "feed": "listing",
      "url": "https://www.fcinternews.it/news/psg-l-enrique-vogliamo-essere-imprevedibili-ecco-perche-stiamo-prendendo-decisioni-magari-difficili-da-capire-989607",
      "local_url": "posts/e038c7181420ca54eaa73beff550e264.html",
      "title_it": "Psg L Enrique Vogliamo Essere Imprevedibili Ecco Perche Stiamo Prendendo Decisioni Magari Difficili Da Capire 989607",
      "title_en": "Psg L Enrique We Want To Be Unpredictable Here's Why We're Making Decisions That May Be Hard To Understand 989607",
      "summary_it": "",
      "summary_en": "",
      "published": "2025-08-21T16:25:22.732704+00:00"
    },
    {
      "id": "0ece126439fdcfe4be0606dcc06083fd",
      "feed": "listing",
      "url": "https://www.fcinternews.it/news/lega-serie-a-torna-la-campagna-stopiracy-per-la-prima-e-seconda-giornata-i-dati-989600",
      "local_url": "posts/0ece126439fdcfe4be0606dcc06083fd.html",
      "title_it": "Lega Serie A Torna La Campagna Stopiracy Per La Prima E Seconda Giornata I Dati 989600",
      "title_en": "League Series A Back The Stopiracy Campaign For The First And Second Day The Data 989600",
      "summary_it": "",
      "summary_en": "",
      "published": "2025-08-21T16:25:22.732704+00:00"
    },
    {
      "id": "f321c5ef1ba30b44a4b975844e77c126",
      "feed": "listing",
      "url": "https://www.fcinternews.it/news/i-corsera-i-san-siro-doppio-fronte-tra-ambulanti-e-ultras-ricorsi-gia-bocciati-mancano-interlocutori-in-curva-989594",
      "local_url": "posts/f321c5ef1ba30b44a4b975844e77c126.html",
      "title_it": "I Corsera I San Siro Doppio Fronte Tra Ambulanti E Ultras Ricorsi Gia Bocciati Mancano Interlocutori In Curva 989594",
      "title_en": "The Corsera I San Siro Double Front Between Ambulants and Ultras Recourses Already Bocciati Missing Interlocutors in Curve 989594",
      "summary_it": "",
      "summary_en": "",
      "published": "2025-08-21T16:25:22.732704+00:00"
    },
    {
      "id": "697db97db5343e9b54e1de8c5dbbc390",
      "feed": "listing",
      "url": "https://www.fcinternews.it/news/i-la-repubblica-i-san-siro-ad-oggi-i-voti-in-consiglio-per-la-delibera-ci-sono-ma-c-e-l-ombra-della-procura-989588",
      "local_url": "posts/697db97db5343e9b54e1de8c5dbbc390.html",
      "title_it": "I La Repubblica I San Siro Ad Oggi I Voti In Consiglio Per La Delibera Ci Sono Ma C E L Ombra Della Procura 989588",
      "title_en": "I La Repubblica I San Siro To Date The Council Votes For The Resolution There Are But C E L Shadow Of The Prosecutor 989588",
      "summary_it": "",
      "summary_en": "",
      "published": "2025-08-21T16:25:22.732704+00:00"
    },
    {
      "id": "2b735da176de0084a0fa6dd9a4ed51c0",
      "feed": "listing",
      "url": "https://www.fcinternews.it/news/natali-solet-piace-all-inter-e-da-top-ma-servono-offerte-importanti-989593",
      "local_url": "posts/2b735da176de0084a0fa6dd9a4ed51c0.html",
      "title_it": "Natali Solet Piace All Inter E Da Top Ma Servono Offerte Importanti 989593",
      "title_en": "Christmas Sole Likes All Inter And From Top But You Need Important Offers 989593",
      "summary_it": "",
      "summary_en": "",
      "published": "2025-08-21T16:25:22.732704+00:00"
    },
    {
      "id": "907ca26c5a273bfe88ca06215aea3d36",
      "feed": "listing",
      "url": "https://www.fcinternews.it/news/serena-ai-limiti-dell-attacco-di-panico-con-l-argentina-la-gaffe-con-la-figlia-di-sacchi-989576",
      "local_url": "posts/907ca26c5a273bfe88ca06215aea3d36.html",
      "title_it": "Serena Ai Limiti Dell Attacco Di Panico Con L Argentina La Gaffe Con La Figlia Di Sacchi 989576",
      "title_en": "Serene At The Limits Of Panic Attack With Argentina La Gaffe With The Daughter Of Bags 989576",
      "summary_it": "",
      "summary_en": "",
      "published": "2025-08-21T16:25:22.732704+00:00"
    },
    {
      "id": "59c5be90639e5308d52782952001b4bd",
      "feed": "listing",
      "url": "https://www.fcinternews.it/news/i-sky-sport-de-i-edson-alvarez-ha-detto-si-al-fenerbahce-il-messicano-era-seguito-anche-da-inter-e-ajax-989597",
      "local_url": "posts/59c5be90639e5308d52782952001b4bd.html",
      "title_it": "I Sky Sport De I Edson Alvarez Ha Detto Si Al Fenerbahce Il Messicano Era Seguito Anche Da Inter E Ajax 989597",
      "title_en": "I Sky Sport De I Edson Alvarez Said Yes At Fenerbahce The Mexican Was Also Followed By Inter And Ajax 989597",
      "summary_it": "",
      "summary_en": "",
      "published": "2025-08-21T16:25:22.732704+00:00"
    },
    {
      "id": "7ba76f1ff58bfc6bf1ea3f2a7c1f4ae4",
      "feed": "listing",
      "url": "https://www.fcinternews.it/news/ufficiale-sector-no-limits-diventa-official-timekeeper-dell-inter-entusiasti-di-questo-nuovo-capitolo-989591",
      "local_url": "posts/7ba76f1ff58bfc6bf1ea3f2a7c1f4ae4.html",
      "title_it": "Ufficiale Sector No Limits Diventa Official Timekeeper Dell Inter Entusiasti Di Questo Nuovo Capitolo 989591",
      "title_en": "Official Sector No Limits Become Official Timekeeper Dell Inter Enthusiasts Of This New Chapter 989591",
      "summary_it": "",
      "summary_en": "",
      "published": "2025-08-21T16:25:22.732704+00:00"
    },
    {
      "id": "d80e8cf48134065e34d26997e452ee79",
      "feed": "listing",
      "url": "https://www.fcinternews.it/news/bergomi-su-asllani-pregio-piu-grande-la-personalita-ma-gli-mancano-le-preventive-989567",
      "local_url": "posts/d80e8cf48134065e34d26997e452ee79.html",
      "title_it": "Bergomi Su Asllani Pregio Piu Grande La Personalita Ma Gli Mancano Le Preventive 989567",
      "title_en": "Bergomes On Asllani Pregio Larger Personality But Missing Preventive 989567",
      "summary_it": "",
      "summary_en": "",
      "published": "2025-08-21T16:25:22.732704+00:00"
    },
    {
      "id": "5c18196fc55b2e71dc72cc26531c6dc0",
      "feed": "listing",
      "url": "https://www.fcinternews.it/news/playoff-champions-league-largo-successo-del-bodo-glimt-e-tre-pareggi-che-tengono-aperti-i-discorsi-989564",
      "local_url": "posts/5c18196fc55b2e71dc72cc26531c6dc0.html",
      "title_it": "Playoff Champions League Largo Successo Del Bodo Glimt E Tre Pareggi Che Tengono Aperti I Discorsi 989564",
      "title_en": "Champions League Playoffs Bodo Glimt Wide Success and Three Draws That Keep Speeches Open 989564",
      "summary_it": "",
      "summary_en": "",
      "published": "2025-08-21T16:25:22.732704+00:00"
    },
    {
      "id": "2754b677afa85dcc7dbe411f5e89e36e",
      "feed": "listing",
      "url": "https://www.fcinternews.it/mercato/il-villarreal-ad-un-passo-da-renato-veiga-il-club-iberico-si-avvicina-alle-richieste-del-chelsea-989548",
      "local_url": "posts/2754b677afa85dcc7dbe411f5e89e36e.html",
      "title_it": "Il Villarreal Ad Un Passo Da Renato Veiga Il Club Iberico Si Avvicina Alle Richieste Del Chelsea 989548",
      "title_en": "Villarreal A Step Away From Renato Veiga The Iberian Club Approaches Chelsea's Requests 989548",
      "summary_it": "",
      "summary_en": "",
      "published": "2025-08-21T16:25:22.732704+00:00"
    },
    {
      "id": "bfd483a98f1d5d507cd0d06a22e8ae2d",
      "feed": "listing",
      "url": "https://www.fcinternews.it/mercato/fontanarosa-la-nota-dell-avellino-il-difensore-ha-firmato-un-contratto-triennale-coi-biancoverdi-989525",
      "local_url": "posts/bfd483a98f1d5d507cd0d06a22e8ae2d.html",
      "title_it": "Fontanarosa La Nota Dell Avellino Il Difensore Ha Firmato Un Contratto Triennale Coi Biancoverdi 989525",
      "title_en": "Fontanarosa The Note Dell Avellino The Defender Signed A Three-Year Contract With Biancoverdi 989525",
      "summary_it": "",
      "summary_en": "",
      "published": "2025-08-21T16:25:22.732704+00:00"
    },
    {
      "id": "6bf519124aee2ec07b2e4cde61b7f546",
      "feed": "listing",
      "url": "https://www.fcinternews.it/mercato/il-como-cerca-un-portiere-fabregas-vorrebbe-inaki-pena-ma-nella-lista-c-e-anche-filip-stankovic-989522",
      "local_url": "posts/6bf519124aee2ec07b2e4cde61b7f546.html",
      "title_it": "Il Como Cerca Un Portiere Fabregas Vorrebbe Inaki Pena Ma Nella Lista C E Anche Filip Stankovic 989522",
      "title_en": "Como looking for a Fabregas Goalkeeper would like Inaki Pena But on List C And also Filip Stankovic 989522",
      "summary_it": "",
      "summary_en": "",
      "published": "2025-08-21T16:25:22.732704+00:00"
    },
    {
      "id": "05ccd1b03aacd34265bf6dc00aad10e4",
      "feed": "listing",
      "url": "https://www.fcinternews.it/mercato/i-from-uk-i-l-inter-ci-prova-per-guehi-sondato-il-terreno-per-prenderlo-a-zero-in-estate-989490",
      "local_url": "posts/05ccd1b03aacd34265bf6dc00aad10e4.html",
      "title_it": "I From Uk I L Inter Ci Prova Per Guehi Sondato Il Terreno Per Prenderlo A Zero In Estate 989490",
      "title_en": "I From UK I L Inter Tests There For Guehi Probed The Ground To Take It To Zero In Summer 989490",
      "summary_it": "",
      "summary_en": "",
      "published": "2025-08-21T16:25:22.732704+00:00"
    },
    {
      "id": "b43476fd12ce1044bbe76474a1b54d3d",
      "feed": "listing",
      "url": "https://www.fcinternews.it/mercato/i-rmc-sport-i-non-si-svende-adrien-rabiot-l-olympique-marsiglia-chiede-circa-15-milioni-989480",
      "local_url": "posts/b43476fd12ce1044bbe76474a1b54d3d.html",
      "title_it": "I Rmc Sport I Non Si Svende Adrien Rabiot L Olympique Marsiglia Chiede Circa 15 Milioni 989480",
      "title_en": "Rmc Sport I Not for Sale Adrien Rabiot L Olympique Marseille Asks Approximately 15 Million 989480",
      "summary_it": "",
      "summary_en": "",
      "published": "2025-08-21T16:25:22.732704+00:00"
    },
    {
      "id": "591b11219e4c646c1ee46bcda90cb3a5",
      "feed": "listing",
      "url": "https://www.fcinternews.it/mercato/palacios-il-rayo-vallecano-mette-la-freccia-accordo-con-l-inter-superato-l-olympiacos-989478",
      "local_url": "posts/591b11219e4c646c1ee46bcda90cb3a5.html",
      "title_it": "Palacios Il Rayo Vallecano Mette La Freccia Accordo Con L Inter Superato L Olympiacos 989478",
      "title_en": "Palacios Il Rayo Vallecano Pette La Freccia Accord con L Inter Superato L Olympiacos 989478",
      "summary_it": "",
      "summary_en": "",
      "published": "2025-08-21T16:25:22.732704+00:00"
    },
    {
      "id": "69c816e435cba12734510319030c18c4",
      "feed": "listing",
      "url": "https://www.fcinternews.it/mercato/i-si-i-capitolo-asllani-la-strada-tra-inter-e-bologna-e-tracciata-si-cerca-la-quadra-definitiva-989418",
      "local_url": "posts/69c816e435cba12734510319030c18c4.html",
      "title_it": "I Si I Capitolo Asllani La Strada Tra Inter E Bologna E Tracciata Si Cerca La Quadra Definitiva 989418",
      "title_en": "I Yes I Chapter Asllani The road between Inter and Bologna and Traced We are looking for the Definitive Square 989418",
      "summary_it": "",
      "summary_en": "",
      "published": "2025-08-21T16:25:22.732704+00:00"
    },
    {
      "id": "f084f01bba8af7baf90fc580fb0cf427",
      "feed": "listing",
      "url": "https://www.fcinternews.it/mercato/i-si-i-lookman-atteso-a-zingonia-nella-giornata-di-mercoledi-quale-futuro-per-il-nigeriano-989417",
      "local_url": "posts/f084f01bba8af7baf90fc580fb0cf427.html",
      "title_it": "I Si I Lookman Atteso A Zingonia Nella Giornata Di Mercoledi Quale Futuro Per Il Nigeriano 989417",
      "title_en": "I Yes I Lookman Expected In Zingonia On Wednesday What Future For The Nigerian 989417",
      "summary_it": "",
      "summary_en": "",
      "published": "2025-08-21T16:25:22.732704+00:00"
    },
    {
      "id": "6fac3c5f065930deb9c61743d00b9e33",
      "feed": "listing",
      "url": "https://www.fcinternews.it/mercato/che-ne-sara-di-lookman-romano-qualche-club-della-premier-league-sta-iniziando-a-chiamare-989413",
      "local_url": "posts/6fac3c5f065930deb9c61743d00b9e33.html",
      "title_it": "Che Ne Sara Di Lookman Romano Qualche Club Della Premier League Sta Iniziando A Chiamare 989413",
      "title_en": "That Ne Sara Di Lookman Romano Some Premier League Clubs Are Starting To Call 989413",
      "summary_it": "",
      "summary_en": "",
      "published": "2025-08-21T16:25:22.732704+00:00"
    },
    {
      "id": "9f97b260e2ef0be160829f9d930b266c",
      "feed": "listing",
      "url": "https://www.fcinternews.it/mercato/saluta-l-inter-amadou-sarr-l-attaccante-classe-2004-passa-a-titolo-definitivo-all-albinoleffe-989410",
      "local_url": "posts/9f97b260e2ef0be160829f9d930b266c.html",
      "title_it": "Saluta L Inter Amadou Sarr L Attaccante Classe 2004 Passa A Titolo Definitivo All Albinoleffe 989410",
      "title_en": "Greet L Inter Amadou Sarr L Attacker Class 2004 Passes to Definitive Title All Albinoleffe 989410",
      "summary_it": "",
      "summary_en": "",
      "published": "2025-08-21T16:25:22.732704+00:00"
    },
    {
      "id": "0304ecc17fd32179dd5caf7d72319c32",
      "feed": "listing",
      "url": "https://www.fcinternews.it/in-primo-piano/l-inter-spunta-un-nome-nuovo-a-centrocampo-pronti-25-milioni-di-euro-per-andy-diouf-superato-il-napoli-989609",
      "local_url": "posts/0304ecc17fd32179dd5caf7d72319c32.html",
      "title_it": "L Inter Spunta Un Nome Nuovo A Centrocampo Pronti 25 Milioni Di Euro Per Andy Diouf Superato Il Napoli 989609",
      "title_en": "L Inter Tick A New Name At Midfield Ready 25 Million Euro For Andy Diouf Passed Naples 989609",
      "summary_it": "",
      "summary_en": "",
      "published": "2025-08-21T16:25:22.732704+00:00"
    },
    {
      "id": "1ecb07c97e66d7c9b05ae3c94721e0d2",
      "feed": "listing",
      "url": "https://www.fcinternews.it/in-primo-piano/romano-asllani-al-torino-cifre-confermate-per-l-inter-anche-il-20-sulla-futura-rivendita-in-caso-di-riscatto-989606",
      "local_url": "posts/1ecb07c97e66d7c9b05ae3c94721e0d2.html",
      "title_it": "Romano Asllani Al Torino Cifre Confermate Per L Inter Anche Il 20 Sulla Futura Rivendita In Caso Di Riscatto 989606",
      "title_en": "Romano Asllani Al Torino Confirmed Figures For The Inter Even On The 20th On The Future Resale In Case Of Redemption 989606",
      "summary_it": "",
      "summary_en": "",
      "published": "2025-08-21T16:25:22.732704+00:00"
    },
    {
      "id": "80485694fba6f1db9d6b10ea6054bb3d",
      "feed": "listing",
      "url": "https://www.fcinternews.it/in-primo-piano/asllani-torino-e-fatta-scambio-di-documenti-in-corso-e-visite-nelle-prossime-ore-989603",
      "local_url": "posts/80485694fba6f1db9d6b10ea6054bb3d.html",
      "title_it": "Asllani Torino E Fatta Scambio Di Documenti In Corso E Visite Nelle Prossime Ore 989603",
      "title_en": "Asllani Turin and Fatta Exchange of Documents in progress and visits in the next hours 989603",
      "summary_it": "",
      "summary_en": "",
      "published": "2025-08-21T16:25:22.732704+00:00"
    },
    {
      "id": "45df602fb3aaca8dacd2bb8de13dde35",
      "feed": "listing",
      "url": "https://www.fcinternews.it/in-primo-piano/i-tmw-i-asllani-sempre-piu-vicino-al-torino-prestito-con-obbligo-condizionato-le-cifre-dell-operazione-989583",
      "local_url": "posts/45df602fb3aaca8dacd2bb8de13dde35.html",
      "title_it": "I Tmw I Asllani Sempre Piu Vicino Al Torino Prestito Con Obbligo Condizionato Le Cifre Dell Operazione 989583",
      "title_en": "I Tmw I Asllani Always Closer to Turin Loan With Conditional Obligation The Figures of Operation 989583",
      "summary_it": "",
      "summary_en": "",
      "published": "2025-08-21T16:25:22.732704+00:00"
    },
    {
      "id": "d8e87867ef5b6735dfa6ded8d2f6170b",
      "feed": "listing",
      "url": "https://www.fcinternews.it/in-primo-piano/i-gds-i-l-inter-copre-i-suoi-due-mister-x-per-evitare-altre-beffe-dopo-lookman-e-kone-80-milioni-da-poter-spendere-989571",
      "local_url": "posts/d8e87867ef5b6735dfa6ded8d2f6170b.html",
      "title_it": "I Gds I L Inter Copre I Suoi Due Mister X Per Evitare Altre Beffe Dopo Lookman E Kone 80 Milioni Da Poter Spendere 989571",
      "title_en": "The GDS I L Inter Covers His Two Mister X's To Avoid More Mistakes After Lookman And KONE 80 Million To Spend 989571",
      "summary_it": "",
      "summary_en": "",
      "published": "2025-08-21T16:25:22.732704+00:00"
    },
    {
      "id": "727fcd780e7645a98261f5a233e1e975",
      "feed": "listing",
      "url": "https://www.fcinternews.it/in-primo-piano/i-sky-i-asllani-intesa-a-un-passo-tra-inter-e-torino-domani-nuovi-contatti-per-chiudere-l-operazione-989570",
      "local_url": "posts/727fcd780e7645a98261f5a233e1e975.html",
      "title_it": "I Sky I Asllani Intesa A Un Passo Tra Inter E Torino Domani Nuovi Contatti Per Chiudere L Operazione 989570",
      "title_en": "I Sky I Asllani Intesa A Step Away Between Inter and Turin Tomorrow New Contacts To Close Transaction 989570",
      "summary_it": "",
      "summary_en": "",
      "published": "2025-08-21T16:25:22.732704+00:00"
    },
    {
      "id": "64e6ef6af082345ad35cd4649bcfbede",
      "feed": "listing",
      "url": "https://www.fcinternews.it/in-primo-piano/i-sky-i-asllani-bologna-nessun-accordo-sull-ingaggio-adesso-e-piu-vicino-al-torino-ecco-la-proposta-989559",
      "local_url": "posts/64e6ef6af082345ad35cd4649bcfbede.html",
      "title_it": "I Sky I Asllani Bologna Nessun Accordo Sull Ingaggio Adesso E Piu Vicino Al Torino Ecco La Proposta 989559",
      "title_en": "I Sky I Asllani Bologna No Agreement On Engagement Now And Closer To Turin Here Is Proposal 989559",
      "summary_it": "",
      "summary_en": "",
      "published": "2025-08-21T16:25:22.732704+00:00"
    },
    {
      "id": "3feecdb5901aaaf2f059907a81cb87b8",
      "feed": "listing",
      "url": "https://www.fcinternews.it/in-primo-piano/caso-rabiot-benatia-indietro-non-si-torna-un-club-per-lui-lo-troveremo-il-telefono-squilla-da-martedi-989553",
      "local_url": "posts/3feecdb5901aaaf2f059907a81cb87b8.html",
      "title_it": "Caso Rabiot Benatia Indietro Non Si Torna Un Club Per Lui Lo Troveremo Il Telefono Squilla Da Martedi 989553",
      "title_en": "Case Rabiot Benatia Back You don't come back a club for him We'll find him The phone rings from Tuesday 989553",
      "summary_it": "",
      "summary_en": "",
      "published": "2025-08-21T16:25:22.732704+00:00"
    },
    {
      "id": "158c8dac1bd215318b173b35234229c6",
      "feed": "listing",
      "url": "https://www.fcinternews.it/in-primo-piano/i-il-romanista-i-roma-servono-100-mln-di-plusvalenze-bloccando-manu-kone-all-inter-il-problema-e-solo-rimandato-989542",
      "local_url": "posts/158c8dac1bd215318b173b35234229c6.html",
      "title_it": "I Il Romanista I Roma Servono 100 Mln Di Plusvalenze Bloccando Manu Kone All Inter Il Problema E Solo Rimandato 989542",
      "title_en": "I Il Romanista I Roma Need 100 Mln Capital Gains Blocking Manu Kone All Inter The Problem And Only Postponed 989542",
      "summary_it": "",
      "summary_en": "",
      "published": "2025-08-21T16:25:22.732704+00:00"
    },
    {
      "id": "7a7cdef2c2518f4773e15c2879563cc9",
      "feed": "listing",
      "url": "https://www.fcinternews.it/in-primo-piano/i-sm-i-asllani-il-bologna-vuole-il-prestito-ma-l-inter-punta-all-incasso-e-poi-resta-da-convincere-il-giocatore-989533",
      "local_url": "posts/7a7cdef2c2518f4773e15c2879563cc9.html",
      "title_it": "I Sm I Asllani Il Bologna Vuole Il Prestito Ma L Inter Punta All Incasso E Poi Resta Da Convincere Il Giocatore 989533",
      "title_en": "I Sm I Asllani Il Bologna Wants The Loan But L Inter Punta All Collection And Then It Remains To Convince The Player 989533",
      "summary_it": "",
      "summary_en": "",
      "published": "2025-08-21T16:25:22.732704+00:00"
    },
    {
      "id": "76fa42e07e7459a96f5d80425b786732",
      "feed": "listing",
      "url": "https://www.fcinternews.it/focus/bastoni-non-ho-dubbi-che-andra-bene-con-chivu-ecco-cosa-e-cambiato-rispetto-alla-gestione-inzaghi-989611",
      "local_url": "posts/76fa42e07e7459a96f5d80425b786732.html",
      "title_it": "Bastoni Non Ho Dubbi Che Andra Bene Con Chivu Ecco Cosa E Cambiato Rispetto Alla Gestione Inzaghi 989611",
      "title_en": "Canes I have no doubt that goes well with Chivu Here's what has changed compared to managing laps 989611",
      "summary_it": "",
      "summary_en": "",
      "published": "2025-08-21T16:25:22.732704+00:00"
    },
    {
      "id": "23f657fc3a320408c2d29cc6276ec33a",
      "feed": "listing",
      "url": "https://www.fcinternews.it/focus/i-la-stampa-i-asllani-al-torino-in-serata-prevista-l-ufficialita-l-albanese-pronto-per-la-gara-dell-ex-con-l-inter-989608",
      "local_url": "posts/23f657fc3a320408c2d29cc6276ec33a.html",
      "title_it": "I La Stampa I Asllani Al Torino In Serata Prevista L Ufficialita L Albanese Pronto Per La Gara Dell Ex Con L Inter 989608",
      "title_en": "I La Stampa I Asllani Al Torino In the Evening L Ufficialita L Albanese Ready for the Dell Ex Con L Inter 989608 Race",
      "summary_it": "",
      "summary_en": "",
      "published": "2025-08-21T16:25:22.732704+00:00"
    },
    {
      "id": "ffcc5e8ed077d7c71095342bd7bf6161",
      "feed": "listing",
      "url": "https://www.fcinternews.it/focus/chivu-e-l-esordio-col-torino-il-senso-di-responsabilita-nascondera-le-mie-emozioni-bonny-lavora-sodo-per-migliorarsi-989605",
      "local_url": "posts/ffcc5e8ed077d7c71095342bd7bf6161.html",
      "title_it": "Chivu E L Esordio Col Torino Il Senso Di Responsabilita Nascondera Le Mie Emozioni Bonny Lavora Sodo Per Migliorarsi 989605",
      "title_en": "Chivu And The Beginning With Turin The Sense Of Responsibility Will Hide My Emotions Bonny Works Hard To Improve Herself 989605",
      "summary_it": "",
      "summary_en": "",
      "published": "2025-08-21T16:25:22.732704+00:00"
    },
    {
      "id": "e427605e4f7cf8de400ad7edf69d22ee",
      "feed": "listing",
      "url": "https://www.fcinternews.it/focus/zanetti-lautaro-e-gia-una-bandiera-dell-inter-chivu-va-supportato-dentro-e-fuori-dal-campo-nico-paz-e-fabregas-989602",
      "local_url": "posts/e427605e4f7cf8de400ad7edf69d22ee.html",
      "title_it": "Zanetti Lautaro E Gia Una Bandiera Dell Inter Chivu Va Supportato Dentro E Fuori Dal Campo Nico Paz E Fabregas 989602",
      "title_en": "Zanetti Lautaro E Gia A Dell Inter Chivu Flag Must Be Supported In and Out of Camp Nico Paz E Fabregas 989602",
      "summary_it": "",
      "summary_en": "",
      "published": "2025-08-21T16:25:22.732704+00:00"
    },
    {
      "id": "060c13b398af64b1ed79f3a9d0621e90",
      "feed": "listing",
      "url": "https://www.fcinternews.it/focus/ufficiale-inter-u23-in-attacco-arriva-antonino-la-gumina-la-formula-del-trasferimento-989601",
      "local_url": "posts/060c13b398af64b1ed79f3a9d0621e90.html",
      "title_it": "Ufficiale Inter U23 In Attacco Arriva Antonino La Gumina La Formula Del Trasferimento 989601",
      "title_en": "Officer Inter U23 In Attack Antonino La Gumina Arrives The Transfer Formula 989601",
      "summary_it": "",
      "summary_en": "",
      "published": "2025-08-21T16:25:22.732704+00:00"
    },
    {
      "id": "852ab721f1b2e39a889e2c695b205095",
      "feed": "listing",
      "url": "https://www.fcinternews.it/focus/inter-il-neom-non-molla-per-pavard-galtier-sta-provando-a-convincere-il-difensore-francese-989598",
      "local_url": "posts/852ab721f1b2e39a889e2c695b205095.html",
      "title_it": "Inter Il Neom Non Molla Per Pavard Galtier Sta Provando A Convincere Il Difensore Francese 989598",
      "title_en": "Inter The Non-Spring Neom For Pavard Galtier Is Trying To Convince The French Defender 989598",
      "summary_it": "",
      "summary_en": "",
      "published": "2025-08-21T16:25:22.732704+00:00"
    },
    {
      "id": "9b26c28776a477a391fd426eb58b1265",
      "feed": "listing",
      "url": "https://www.fcinternews.it/focus/i-cds-i-splende-il-sole-sui-conti-dell-inter-merito-di-oaktree-e-del-percorso-tutti-i-numeri-989578",
      "local_url": "posts/9b26c28776a477a391fd426eb58b1265.html",
      "title_it": "I Cds I Splende Il Sole Sui Conti Dell Inter Merito Di Oaktree E Del Percorso Tutti I Numeri 989578",
      "title_en": "CDs I Shines The Sun On Dell Accounts Inter Merit Of Oaktree And The Route All Numbers 989578",
      "summary_it": "",
      "summary_en": "",
      "published": "2025-08-21T16:25:22.732704+00:00"
    },
    {
      "id": "5721267266ce5201621524fd706acdb4",
      "feed": "listing",
      "url": "https://www.fcinternews.it/focus/maresca-mai-chiesto-di-non-arbitrare-il-napoli-uniformita-di-giudizio-su-alcuni-episodi-non-ne-usciremo-mai-989592",
      "local_url": "posts/5721267266ce5201621524fd706acdb4.html",
      "title_it": "Maresca Mai Chiesto Di Non Arbitrare Il Napoli Uniformita Di Giudizio Su Alcuni Episodi Non Ne Usciremo Mai 989592",
      "title_en": "Maresca Never Asked Not To Arbitrate Naples Uniformed Judgment On Some Episodes We Will Never Come Out Of It 989592",
      "summary_it": "",
      "summary_en": "",
      "published": "2025-08-21T16:25:22.732704+00:00"
    },
    {
      "id": "5f3aa081ebfe7fc8ac44ba6026c5b24b",
      "feed": "listing",
      "url": "https://www.fcinternews.it/focus/i-gds-i-pavard-cambia-numero-ma-non-status-il-francese-resta-sul-mercato-989573",
      "local_url": "posts/5f3aa081ebfe7fc8ac44ba6026c5b24b.html",
      "title_it": "I Gds I Pavard Cambia Numero Ma Non Status Il Francese Resta Sul Mercato 989573",
      "title_en": "I GDS I Pavard Change Number But Not Status French Remains on the Market 989573",
      "summary_it": "",
      "summary_en": "",
      "published": "2025-08-21T16:25:22.732704+00:00"
    },
    {
      "id": "6c53a4391e500d85742349daf6aed57e",
      "feed": "listing",
      "url": "https://www.fcinternews.it/focus/i-gds-i-calhanoglu-salta-l-esordio-chivu-lancia-sucic-nel-ruolo-di-regista-989572",
      "local_url": "posts/6c53a4391e500d85742349daf6aed57e.html",
      "title_it": "I Gds I Calhanoglu Salta L Esordio Chivu Lancia Sucic Nel Ruolo Di Regista 989572",
      "title_en": "GDS I Calhanoglu Salta L Esordio Chivu Launches Sucic In The Role Of Director 989572",
      "summary_it": "",
      "summary_en": "",
      "published": "2025-08-21T16:25:22.732704+00:00"
    },
    {
      "id": "dcc3c8b306063ec61433298bad4b4490",
      "feed": "article",
      "url": "https://m.fcinternews.it/focus/de-winter-difficile-dire-no-al-milan-inter-ho-letto-delle-cose-ma-nulla-di-serio-989617",
      "local_url": "posts/dcc3c8b306063ec61433298bad4b4490.html",
      "title_it": "De Winter: \"Difficile dire no al Milan. Inter? Ho letto delle cose, ma nulla di serio\"",
      "title_en": "De Winter: \"Hard to say no to Milan. Inter? I've read things, but nothing serious.”",
      "summary_it": "Durante la conferenza stampa di presentazione come nuovo giocatore del Milan, Koni De Winter ha spiegato che le voci circolate sui media sull&#39;interessamento da parte dell&#39;Inter nei suoi...",
      "summary_en": "During the press conference to present himself as a new AC Milan player, Koni De Winter explained that the rumours circulated in the media about Inter's interest in his...",
      "published": "2025-08-21T16:25:18.024839+00:00"
    },
    {
      "id": "192bcacdbdbae312268aa60fef4810a4",
      "feed": "article",
      "url": "https://m.fcinternews.it/il-resto-del-mercato/ufficiale-torino-senza-sanabria-contro-l-inter-l-attaccante-passa-alla-cremonese-a-titolo-definitivo-989616",
      "local_url": "posts/192bcacdbdbae312268aa60fef4810a4.html",
      "title_it": "UFFICIALE - Torino senza Sanabria contro l'Inter: l'attaccante passa alla Cremonese a titolo definitivo",
      "title_en": "OFFICIAL - Turin without Sanabria against Inter: the striker switches to Cremonese on a permanent basis",
      "summary_it": "Antonio&nbsp;Sanabria&nbsp;non sar&agrave; tra i convocati di Marco Baroni per l&#39;esordio in campionato del Torino contro l&#39;Inter,&nbsp;in programma luned&igrave; 25 agosto, a San Siro....",
      "summary_en": "Antonio Sanabria will not be among those summoned by Marco Baroni for his debut in the Turin championship against Inter, scheduled for Monday, August 25, at San Siro....",
      "published": "2025-08-21T16:25:12.353562+00:00"
    },
    {
      "id": "358b0bdae642a1299e8c4284c51cdc53",
      "feed": "article",
      "url": "https://m.fcinternews.it/il-resto-della-a/milan-athekame-ho-affrontato-inter-e-atalanta-mi-ha-colpito-l-intensita-989618",
      "local_url": "posts/358b0bdae642a1299e8c4284c51cdc53.html",
      "title_it": "Milan, Athekame: \"Ho affrontato Inter e Atalanta, mi ha colpito l'intensità\"",
      "title_en": "Milan, Athekame: \"I faced Inter and Atalanta, I was struck by the intensity\"",
      "summary_it": "Zachary Athekame, nuovo terzino destro del Milan arrivato dallo Young Boys, si &egrave; presentato in conferenza stampa a Casa Milan. Si riportano di seguito le sue dichiarazioni:\r\n\r\nC&#39;&egrave;...",
      "summary_en": "Zachary Athekame, Milan's new right-back from the Young Boys, appeared at a press conference at Casa Milan. Below are his statements:\r\n\r\nThere is...",
      "published": "2025-08-21T16:25:06.356340+00:00"
    },
    {
      "id": "8f951974462cbf174a09561abdd70b50",
      "feed": "article",
      "url": "https://m.fcinternews.it/news/ultimi-giorni-di-mercato-allo-sheraton-milan-san-siro-marotta-partecipera-alla-tavola-rotonda-la-sostenibilita-del-sistema-989620",
      "local_url": "posts/8f951974462cbf174a09561abdd70b50.html",
      "title_it": "Ultimi giorni di mercato allo Sheraton Milan San Siro: Marotta parteciperà alla Tavola rotonda “La sostenibilità del sistema'",
      "title_en": "Last days of the market at the Sheraton Milan San Siro: Marotta will participate in the round table \"The sustainability of the system\"",
      "summary_it": "Negli ultimi giorni del calciomercato italiano, in programma&nbsp;allo Sheraton&nbsp;Milan San Siro, ci sar&agrave; spazio anche per momenti di approfondimento e di confronto organizzati da A.Di.Se. e...",
      "summary_en": "In the last days of the Italian football market, scheduled at the Sheraton Milan San Siro, there will also be space for moments of in-depth study and discussion organized by A.Di.Se. and...",
      "published": "2025-08-21T16:25:00.733144+00:00"
    },
    {
      "id": "7aecad1d9c25eeaa23186e14fa877a67",
      "feed": "article",
      "url": "https://m.fcinternews.it/il-resto-della-a/napoli-de-laurentiis-conte-stakanovista-proprio-come-me-kvara-l-agente-minacciava-di-ricorrere-all-articolo-17-989612",
      "local_url": "posts/7aecad1d9c25eeaa23186e14fa877a67.html",
      "title_it": "Napoli, De Laurentiis: \"Conte stakanovista proprio come me. Kvara? L'agente minacciava di ricorrere all'articolo 17\"",
      "title_en": "Naples, De Laurentiis: \"Count stakanovista just like me. Kvara? The agent threatened to resort to Article 17\"",
      "summary_it": "Aurelio De Laurentiis, presidente del Napoli, sar&agrave; il protagonista dell&rsquo;intervista esclusiva a 7 del Corriere della Sera, a firma di Paolo Cond&ograve;, in uscita...",
      "summary_en": "Aurelio De Laurentiis, president of Napoli, will be the protagonist of the exclusive interview with 7 of Corriere della Sera, signed by Paolo Condò, out...",
      "published": "2025-08-21T16:24:55.119463+00:00"
    },
    {
      "id": "77dee89d5bb6b641e4e4a028a85d47ba",
      "feed": "article",
      "url": "https://m.fcinternews.it/focus/i-rmc-sport-i-diouf-aveva-un-accordo-con-il-napoli-ora-e-tutto-apparecchiato-per-il-passaggio-all-inter-989619",
      "local_url": "posts/77dee89d5bb6b641e4e4a028a85d47ba.html",
      "title_it": "RMC Sport - Diouf aveva un accordo con il Napoli, ora è tutto apparecchiato per il passaggio all'Inter",
      "title_en": "RMC Sport - Diouf had an agreement with Napoli, now everything is set for the transition to Inter",
      "summary_it": "E&#39; tutto apparecchiato per il trasferimento di Andy Diouf&nbsp;dal Lens all&#39;Inter. Lo confermano anche i giornalisti di RMC Sport, spiegando che il club milanese pagher&agrave;&nbsp;20 milioni...",
      "summary_en": "It's all set up for Andy Diouf's transfer from Lens to Inter. This is also confirmed by the journalists of RMC Sport, explaining that the Milanese club will pay 20 million...",
      "published": "2025-08-21T16:24:47.466265+00:00"
    },
    {
      "id": "279f52a711d7a7d17261c694695b2056",
      "feed": "article",
      "url": "https://m.fcinternews.it/focus/inter-lunedi-l-esordio-in-serie-a-contro-il-torino-data-e-orario-della-conferenza-di-chivu-989623",
      "local_url": "posts/279f52a711d7a7d17261c694695b2056.html",
      "title_it": "Inter, lunedì l'esordio in Serie A contro il Torino: data e orario della conferenza di Chivu",
      "title_en": "Inter, on Monday the debut in Serie A against Turin: date and time of the Chivu conference",
      "summary_it": "L&#39;Inter si prepara per ripartire nella nuova stagione, con Cristian Chivu protagonista nella prima conferenza stampa dell&#39;annata 2025/26. I nerazzurri sfideranno il Torino a San Siro...",
      "summary_en": "Inter is preparing to start again in the new season, with Cristian Chivu starring in the first press conference of the 2025/26 vintage. The Nerazzurri will challenge Turin in San Siro...",
      "published": "2025-08-21T16:24:42.188957+00:00"
    },
    {
      "id": "2e5856bd34d5a7eb0281390bae73c0fd",
      "feed": "article",
      "url": "https://m.fcinternews.it/in-primo-piano/i-sky-i-inter-accordo-verbale-col-lens-per-andy-diouf-affare-a-titolo-definitivo-giocatore-domani-a-milano-989610",
      "local_url": "posts/2e5856bd34d5a7eb0281390bae73c0fd.html",
      "title_it": "Sky - Inter, accordo verbale col Lens per Andy Diouf: affare a titolo definitivo. Giocatore domani a Milano?",
      "title_en": "Sky - Inter, verbal agreement with Lens for Andy Diouf: a definitive deal. Player tomorrow in Milan?",
      "summary_it": "Inter e Lens hanno trovato l&#39;accordo verbale&nbsp;per il passaggio di Andy&nbsp;Diouf, centrocampista franco-senegalese classe 2003, alla corte di Cristian Chivu. Si tratta di un affare a titolo...",
      "summary_en": "Inter and Lens have found the verbal agreement for the transfer of Andy Diouf, a French-Senegalese midfielder born in 2003, to the court of Cristian Chivu. This is a bargain in its own right...",
      "published": "2025-08-21T16:24:36.393944+00:00"
    },
    {
      "id": "3aaaee0d87220b37b1fda6cc2fcda600",
      "feed": "article",
      "url": "https://m.fcinternews.it/in-primo-piano/i-l-equipe-i-andy-diouf-all-inter-affare-imminente-pronto-un-quinquennale-al-lens-20-milioni-di-euro-piu-bonus-989613",
      "local_url": "posts/3aaaee0d87220b37b1fda6cc2fcda600.html",
      "title_it": "L'Équipe - Andy Diouf all'Inter, affare imminente: pronto un quinquennale. Al Lens 20 milioni di euro più bonus",
      "title_en": "The Team - Andy Diouf at Inter, business imminent: a five-year deal is ready. Al Lens €20 million plus bonus",
      "summary_it": "L&#39;&Eacute;quipe conferma le indiscrezioni giornalistiche dei media italiani: l&#39;Inter&nbsp;ha messo sul piatto&nbsp;25 milioni di euro, di cui 20 milioni di euro di base fissa pi&ugrave; bonus...",
      "summary_en": "The Team confirms the journalistic indiscretions of the Italian media: Inter have put on the plate 25 million euros, of which 20 million euros of fixed base plus bonuses...",
      "published": "2025-08-21T16:24:30.470833+00:00"
    },
    {
      "id": "e538b43e1355d6bc97b2c5848457a835",
      "feed": "article",
      "url": "https://m.fcinternews.it/in-primo-piano/bastoni-quando-perdi-ci-sono-due-strade-i-nuovi-hanno-qualita-chivu-grande-sorpresa-sul-piano-umano-989624",
      "local_url": "posts/e538b43e1355d6bc97b2c5848457a835.html",
      "title_it": "Bastoni: \"Quando perdi ci sono due strade. I nuovi hanno qualità, Chivu grande sorpresa sul piano umano\"",
      "title_en": "Sticks: \"When you lose there are two roads. The new ones have quality, Chivu a great surprise on the human level\"",
      "summary_it": "Lunga intervista per il difensore Alessandro Bastoni ai microfoni di Sky Sport Insider. Il difensore nerazzurro torna sui rimpianti relativi alla passata stagione: &ldquo;Dopo le delusioni del finale...",
      "summary_en": "Long interview for defender Alessandro Bastoni on Sky Sport Insider microphones. The Nerazzurri defender returns to the regrets of last season: \"After the disappointments of the final...",
      "published": "2025-08-21T16:24:25.121314+00:00"
    },
    {
      "id": "5332359596c70dc7944f50d6c2674ea4",
      "feed": "article",
      "url": "https://www.fcinternews.it/focus/de-winter-difficile-dire-no-al-milan-inter-ho-letto-delle-cose-ma-nulla-di-serio-989617",
      "local_url": "posts/5332359596c70dc7944f50d6c2674ea4.html",
      "title_it": "De Winter: \"Difficile dire no al Milan. Inter? Ho letto delle cose, ma nulla di serio\"",
      "title_en": "De Winter: \"Hard to say no to Milan. Inter? I've read things, but nothing serious.”",
      "summary_it": "Durante la conferenza stampa di presentazione come nuovo giocatore del Milan, Koni De Winter ha spiegato che le voci circolate sui media sull&#39;interessamento da parte dell&#39;Inter nei suoi...",
      "summary_en": "During the press conference to present himself as a new AC Milan player, Koni De Winter explained that the rumours circulated in the media about Inter's interest in his...",
      "published": "2025-08-21T16:24:19.464373+00:00"
    },
    {
      "id": "88880ca50b9484a6bca82407df5c1705",
      "feed": "article",
      "url": "https://www.fcinternews.it/il-resto-del-mercato/ufficiale-torino-senza-sanabria-contro-l-inter-l-attaccante-passa-alla-cremonese-a-titolo-definitivo-989616",
      "local_url": "posts/88880ca50b9484a6bca82407df5c1705.html",
      "title_it": "UFFICIALE - Torino senza Sanabria contro l'Inter: l'attaccante passa alla Cremonese a titolo definitivo",
      "title_en": "OFFICIAL - Turin without Sanabria against Inter: the striker switches to Cremonese on a permanent basis",
      "summary_it": "Antonio&nbsp;Sanabria&nbsp;non sar&agrave; tra i convocati di Marco Baroni per l&#39;esordio in campionato del Torino contro l&#39;Inter,&nbsp;in programma luned&igrave; 25 agosto, a San Siro....",
      "summary_en": "Antonio Sanabria will not be among those summoned by Marco Baroni for his debut in the Turin championship against Inter, scheduled for Monday, August 25, at San Siro....",
      "published": "2025-08-21T16:24:14.507919+00:00"
    },
    {
      "id": "dbbde276cede88d8e66dd0a78098fa21",
      "feed": "article",
      "url": "https://www.fcinternews.it/il-resto-della-a/milan-athekame-ho-affrontato-inter-e-atalanta-mi-ha-colpito-l-intensita-989618",
      "local_url": "posts/dbbde276cede88d8e66dd0a78098fa21.html",
      "title_it": "Milan, Athekame: \"Ho affrontato Inter e Atalanta, mi ha colpito l'intensità\"",
      "title_en": "Milan, Athekame: \"I faced Inter and Atalanta, I was struck by the intensity\"",
      "summary_it": "Zachary Athekame, nuovo terzino destro del Milan arrivato dallo Young Boys, si &egrave; presentato in conferenza stampa a Casa Milan. Si riportano di seguito le sue dichiarazioni:\r\n\r\nC&#39;&egrave;...",
      "summary_en": "Zachary Athekame, Milan's new right-back from the Young Boys, appeared at a press conference at Casa Milan. Below are his statements:\r\n\r\nThere is...",
      "published": "2025-08-21T16:24:09.334266+00:00"
    },
    {
      "id": "8112ecf3be0890f61f2e375d4104c62a",
      "feed": "article",
      "url": "https://www.fcinternews.it/news/ultimi-giorni-di-mercato-allo-sheraton-milan-san-siro-marotta-partecipera-alla-tavola-rotonda-la-sostenibilita-del-sistema-989620",
      "local_url": "posts/8112ecf3be0890f61f2e375d4104c62a.html",
      "title_it": "Ultimi giorni di mercato allo Sheraton Milan San Siro: Marotta parteciperà alla Tavola rotonda “La sostenibilità del sistema'",
      "title_en": "Last days of the market at the Sheraton Milan San Siro: Marotta will participate in the round table \"The sustainability of the system\"",
      "summary_it": "Negli ultimi giorni del calciomercato italiano, in programma&nbsp;allo Sheraton&nbsp;Milan San Siro, ci sar&agrave; spazio anche per momenti di approfondimento e di confronto organizzati da A.Di.Se. e...",
      "summary_en": "In the last days of the Italian football market, scheduled at the Sheraton Milan San Siro, there will also be space for moments of in-depth study and discussion organized by A.Di.Se. and...",
      "published": "2025-08-21T16:24:03.873082+00:00"
    },
    {
      "id": "4cdc0a977a27ae14756754d500c61ba9",
      "feed": "article",
      "url": "https://www.fcinternews.it/il-resto-della-a/napoli-de-laurentiis-conte-stakanovista-proprio-come-me-kvara-l-agente-minacciava-di-ricorrere-all-articolo-17-989612",
      "local_url": "posts/4cdc0a977a27ae14756754d500c61ba9.html",
      "title_it": "Napoli, De Laurentiis: \"Conte stakanovista proprio come me. Kvara? L'agente minacciava di ricorrere all'articolo 17\"",
      "title_en": "Naples, De Laurentiis: \"Count stakanovista just like me. Kvara? The agent threatened to resort to Article 17\"",
      "summary_it": "Aurelio De Laurentiis, presidente del Napoli, sar&agrave; il protagonista dell&rsquo;intervista esclusiva a 7 del Corriere della Sera, a firma di Paolo Cond&ograve;, in uscita...",
      "summary_en": "Aurelio De Laurentiis, president of Napoli, will be the protagonist of the exclusive interview with 7 of Corriere della Sera, signed by Paolo Condò, out...",
      "published": "2025-08-21T16:23:58.539487+00:00"
    },
    {
      "id": "4b05f5b58bd78637d28422bf8eda50b3",
      "feed": "article",
      "url": "https://www.fcinternews.it/focus/i-rmc-sport-i-diouf-aveva-un-accordo-con-il-napoli-ora-e-tutto-apparecchiato-per-il-passaggio-all-inter-989619",
      "local_url": "posts/4b05f5b58bd78637d28422bf8eda50b3.html",
      "title_it": "RMC Sport - Diouf aveva un accordo con il Napoli, ora è tutto apparecchiato per il passaggio all'Inter",
      "title_en": "RMC Sport - Diouf had an agreement with Napoli, now everything is set for the transition to Inter",
      "summary_it": "E&#39; tutto apparecchiato per il trasferimento di Andy Diouf&nbsp;dal Lens all&#39;Inter. Lo confermano anche i giornalisti di RMC Sport, spiegando che il club milanese pagher&agrave;&nbsp;20 milioni...",
      "summary_en": "It's all set up for Andy Diouf's transfer from Lens to Inter. This is also confirmed by the journalists of RMC Sport, explaining that the Milanese club will pay 20 million...",
      "published": "2025-08-21T16:23:53.363347+00:00"
    },
    {
      "id": "99e2e0eef93f6d6a467424e641dbe56b",
      "feed": "article",
      "url": "https://www.fcinternews.it/focus/inter-lunedi-l-esordio-in-serie-a-contro-il-torino-data-e-orario-della-conferenza-di-chivu-989623",
      "local_url": "posts/99e2e0eef93f6d6a467424e641dbe56b.html",
      "title_it": "Inter, lunedì l'esordio in Serie A contro il Torino: data e orario della conferenza di Chivu",
      "title_en": "Inter, on Monday the debut in Serie A against Turin: date and time of the Chivu conference",
      "summary_it": "L&#39;Inter si prepara per ripartire nella nuova stagione, con Cristian Chivu protagonista nella prima conferenza stampa dell&#39;annata 2025/26. I nerazzurri sfideranno il Torino a San Siro...",
      "summary_en": "Inter is preparing to start again in the new season, with Cristian Chivu starring in the first press conference of the 2025/26 vintage. The Nerazzurri will challenge Turin in San Siro...",
      "published": "2025-08-21T16:23:47.761740+00:00"
    },
    {
      "id": "169a14e2d3547f29ed035201636a2500",
      "feed": "article",
      "url": "https://www.fcinternews.it/in-primo-piano/i-sky-i-inter-accordo-verbale-col-lens-per-andy-diouf-affare-a-titolo-definitivo-giocatore-domani-a-milano-989610",
      "local_url": "posts/169a14e2d3547f29ed035201636a2500.html",
      "title_it": "Sky - Inter, accordo verbale col Lens per Andy Diouf: affare a titolo definitivo. Giocatore domani a Milano?",
      "title_en": "Sky - Inter, verbal agreement with Lens for Andy Diouf: a definitive deal. Player tomorrow in Milan?",
      "summary_it": "Inter e Lens hanno trovato l&#39;accordo verbale&nbsp;per il passaggio di Andy&nbsp;Diouf, centrocampista franco-senegalese classe 2003, alla corte di Cristian Chivu. Si tratta di un affare a titolo...",
      "summary_en": "Inter and Lens have found the verbal agreement for the transfer of Andy Diouf, a French-Senegalese midfielder born in 2003, to the court of Cristian Chivu. This is a bargain in its own right...",
      "published": "2025-08-21T16:23:42.424599+00:00"
    },
    {
      "id": "e1425239860ad42203bd963ccfacbca0",
      "feed": "article",
      "url": "https://www.fcinternews.it/in-primo-piano/i-l-equipe-i-andy-diouf-all-inter-affare-imminente-pronto-un-quinquennale-al-lens-20-milioni-di-euro-piu-bonus-989613",
      "local_url": "posts/e1425239860ad42203bd963ccfacbca0.html",
      "title_it": "L'Équipe - Andy Diouf all'Inter, affare imminente: pronto un quinquennale. Al Lens 20 milioni di euro più bonus",
      "title_en": "The Team - Andy Diouf at Inter, business imminent: a five-year deal is ready. Al Lens €20 million plus bonus",
      "summary_it": "L&#39;&Eacute;quipe conferma le indiscrezioni giornalistiche dei media italiani: l&#39;Inter&nbsp;ha messo sul piatto&nbsp;25 milioni di euro, di cui 20 milioni di euro di base fissa pi&ugrave; bonus...",
      "summary_en": "The Team confirms the journalistic indiscretions of the Italian media: Inter have put on the plate 25 million euros, of which 20 million euros of fixed base plus bonuses...",
      "published": "2025-08-21T16:23:36.787466+00:00"
    },
    {
      "id": "8ddd3b99f46f64e832411f121691d3fb",
      "feed": "article",
      "url": "https://www.fcinternews.it/in-primo-piano/bastoni-quando-perdi-ci-sono-due-strade-i-nuovi-hanno-qualita-chivu-grande-sorpresa-sul-piano-umano-989624",
      "local_url": "posts/8ddd3b99f46f64e832411f121691d3fb.html",
      "title_it": "Bastoni: \"Quando perdi ci sono due strade. I nuovi hanno qualità, Chivu grande sorpresa sul piano umano\"",
      "title_en": "Sticks: \"When you lose there are two roads. The new ones have quality, Chivu a great surprise on the human level\"",
      "summary_it": "Lunga intervista per il difensore Alessandro Bastoni ai microfoni di Sky Sport Insider. Il difensore nerazzurro torna sui rimpianti relativi alla passata stagione: &ldquo;Dopo le delusioni del finale...",
      "summary_en": "Long interview for defender Alessandro Bastoni on Sky Sport Insider microphones. The Nerazzurri defender returns to the regrets of last season: \"After the disappointments of the final...",
      "published": "2025-08-21T16:23:31.217606+00:00"
    }
  ]
}